{
  "project_info": {
    "project_number": "84423144967",
    "firebase_url": "https://psych-753c4.firebaseio.com",
    "project_id": "psych-753c4",
    "storage_bucket": "psych-753c4.appspot.com"
  },
  "client": [
    {
      "client_info": {
        "mobilesdk_app_id": "1:84423144967:android:b8466f994c38f2e0f5dca2",
        "android_client_info": {
          "package_name": "soumyagupta2307.questn"
        }
      },
      "oauth_client": [
        {
          "client_id": "84423144967-5cr3db4m3jv6m175g6fholactk5880dn.apps.googleusercontent.com",
          "client_type": 3
        }
      ],
      "api_key": [
        {
          "current_key": "AIzaSyBqGUG4S0GUOkVikUyq1CIgRW0x49Xy4iI"
        }
      ],
      "services": {
        "appinvite_service": {
          "other_platform_oauth_client": [
            {
              "client_id": "84423144967-5cr3db4m3jv6m175g6fholactk5880dn.apps.googleusercontent.com",
              "client_type": 3
            },
            {
              "client_id": "84423144967-a6c3kskc44nr39e5tbo41mjhh59rirhg.apps.googleusercontent.com",
              "client_type": 2,
              "ios_info": {
                "bundle_id": "soumyagupta2307-gmail.com.psych"
              }
            }
          ]
        }
      }
    }
  ],
  "configuration_version": "1"
}